[  
   {  
      "_id":"59295c02839991f4505f6536",
      "name":"mocha_card_1",
      "__v":0,
      "facess":[  
         {  
            "ordernum":0,
            "symbol":"trans-card",
            "text":"mocha card transcript",
            "sound":false,
            "previewDisplay":true,
            "_id":"59295c02839991f4505f653a"
         },
         {  
            "ordernum":1,
            "symbol":"heb-card",
            "text":"mocha card heb",
            "sound":false,
            "previewDisplay":true,
            "_id":"59295c02839991f4505f6539"
         },
         {  
            "ordernum":2,
            "symbol":"eng-card",
            "text":"mocha card eng",
            "sound":false,
            "previewDisplay":true,
            "_id":"59295c02839991f4505f6538"
         },
         {  
            "ordernum":0,
            "symbol":"arb-card",
            "text":"mocha card arb",
            "sound":false,
            "previewDisplay":true,
            "_id":"59295c02839991f4505f6537"
         }
      ],
      "category":[  
         "59295c01839991f4505f652c"
      ]
   },
   {  
      "_id":"59295c03839991f4505f653b",
      "name":"mocha_card_2",
      "__v":0,
      "facess":[  
         {  
            "ordernum":0,
            "symbol":"trans-card",
            "text":"2 mocha card transcript",
            "sound":false,
            "previewDisplay":true,
            "_id":"59295c03839991f4505f653f"
         },
         {  
            "ordernum":1,
            "symbol":"heb-card",
            "text":"2 mocha card heb",
            "sound":false,
            "previewDisplay":true,
            "_id":"59295c03839991f4505f653e"
         },
         {  
            "ordernum":2,
            "symbol":"eng-card",
            "text":"2 mocha card eng",
            "sound":false,
            "previewDisplay":true,
            "_id":"59295c03839991f4505f653d"
         },
         {  
            "ordernum":0,
            "symbol":"arb-card",
            "text":"2 mocha card arb",
            "sound":false,
            "previewDisplay":true,
            "_id":"59295c03839991f4505f653c"
         }
      ],
      "category":[  
         "59295c01839991f4505f652c"
      ]
   }
]